response_time_analysis/__init__.py
response_time_analysis/analysis/__init__.py
response_time_analysis/analysis/edf.py
response_time_analysis/analysis/fifo.py
response_time_analysis/analysis/fp.py
response_time_analysis/analysis/solve.py
response_time_analysis/iter.py
response_time_analysis/model/__init__.py
response_time_analysis/model/arrival.py
response_time_analysis/model/execution.py
response_time_analysis/model/policy.py
response_time_analysis/model/supply.py
response_time_analysis/model/task.py
response_time_analysis/model/time.py
response_time_analysis/model/workload.py
response_time_analysis/py.typed
response_time_analysis-0.1.1.dist-info/licenses/LICENSE
response_time_analysis-0.1.1.dist-info/WHEEL
response_time_analysis-0.1.1.dist-info/METADATA
response_time_analysis-0.1.1.dist-info/RECORD
