Metadata-Version: 2.4
Name: response-time-analysis
Version: 0.1.1
Summary: An implementation of the response-time analyses (RTAs) verified by the PROSA project
Author: Björn Brandenburg
Author-email: Björn Brandenburg <bbb@mpi-sws.org>
License-Expression: MIT
License-File: LICENSE
Classifier: Programming Language :: Python :: 3
Classifier: Operating System :: OS Independent
Classifier: Topic :: Scientific/Engineering
Requires-Python: >=3.10
Project-URL: Homepage, https://prosa.mpi-sws.org
Project-URL: Issues, https://gitlab.mpi-sws.org/RT-PROOFS/pyRTA/-/issues
Project-URL: Repository, https://gitlab.mpi-sws.org/RT-PROOFS/pyRTA.git
